setup.py
wyh/__init__.py
wyh/wyh.py
wyh.egg-info/PKG-INFO
wyh.egg-info/SOURCES.txt
wyh.egg-info/dependency_links.txt
wyh.egg-info/not-zip-safe
wyh.egg-info/top_level.txt