Metadata-Version: 1.0
Name: wyh
Version: 0.0.1
Summary: this is evan first test python egg
Home-page: UNKNOWN
Author: evan
Author-email: 824452323@qq.com
License: UNKNOWN
Keywords: test,wyh
Platform: UNKNOWN
